{"queryCost": 1, "latitude": 45.682, "longitude": -122.574, "resolvedAddress": "45.68200,-122.57400", "address": "45.68200,-122.57400", "timezone": "America/Los_Angeles", "tzoffset": -8.0, "days": [{"datetime": "2016-03-13", "datetimeEpoch": 1457856000, "tempmax": 52.9, "tempmin": 43.1, "temp": 46.3, "feelslikemax": 52.9, "feelslikemin": 35.7, "feelslike": 41.8, "dew": 40.9, "humidity": 81.8, "precip": 0.58, "precipprob": 100.0, "precipcover": 50.0, "preciptype": ["rain"], "snow": 0.0, "snowdepth": 0.0, "windgust": 36.2, "windspeed": 19.6, "winddir": 158.7, "pressure": 1000.9, "cloudcover": 95.6, "visibility": 9.1, "solarradiation": 65.2, "solarenergy": 5.4, "uvindex": 3.0, "sunrise": "07:25:25", "sunriseEpoch": 1457879125, "sunset": "19:14:25", "sunsetEpoch": 1457921665, "moonphase": 0.13, "conditions": "Rain, Overcast", "description": "Cloudy skies throughout the day with a chance of rain throughout the day.", "icon": "rain", "stations": ["72698524242", "KVUO", "KPDX", "72698024229", "KTTD", "72791894298"], "source": "obs"}], "stations": {"72698524242": {"distance": 19427.0, "latitude": 45.551, "longitude": -122.409, "useCount": 0, "id": "72698524242", "name": "PORTLAND TROUTDALE AIRPORT, OR US", "quality": 100, "contribution": 0.0}, "KVUO": {"distance": 9614.0, "latitude": 45.62, "longitude": -122.66, "useCount": 0, "id": "KVUO", "name": "KVUO", "quality": 100, "contribution": 0.0}, "KPDX": {"distance": 9350.0, "latitude": 45.6, "longitude": -122.6, "useCount": 0, "id": "KPDX", "name": "KPDX", "quality": 100, "contribution": 0.0}, "72698024229": {"distance": 9975.0, "latitude": 45.596, "longitude": -122.609, "useCount": 0, "id": "72698024229", "name": "PORTLAND INTERNATIONAL AIRPORT, OR US", "quality": 100, "contribution": 0.0}, "KTTD": {"distance": 18966.0, "latitude": 45.55, "longitude": -122.42, "useCount": 0, "id": "KTTD", "name": "KTTD", "quality": 100, "contribution": 0.0}, "72791894298": {"distance": 9388.0, "latitude": 45.621, "longitude": -122.657, "useCount": 0, "id": "72791894298", "name": "VANCOUVER PEARSON AIRPORT, WA US", "quality": 100, "contribution": 0.0}}}