{"queryCost": 1, "latitude": 38.275, "longitude": -104.564, "resolvedAddress": "38.27500,-104.56400", "address": "38.27500,-104.56400", "timezone": "America/Denver", "tzoffset": -6.0, "days": [{"datetime": "2016-03-24", "datetimeEpoch": 1458799200, "tempmax": 58.9, "tempmin": 18.0, "temp": 39.0, "feelslikemax": 58.9, "feelslikemin": 18.0, "feelslike": 36.9, "dew": 18.1, "humidity": 49.8, "precip": 0.0, "precipprob": 0.0, "precipcover": 0.0, "preciptype": null, "snow": 0.0, "snowdepth": 0.0, "windgust": 23.0, "windspeed": 14.9, "winddir": 175.5, "pressure": 1016.4, "cloudcover": 0.2, "visibility": 9.9, "solarradiation": 270.0, "solarenergy": 23.5, "uvindex": 9.0, "sunrise": "06:54:36", "sunriseEpoch": 1458824076, "sunset": "19:14:35", "sunsetEpoch": 1458868475, "moonphase": 0.51, "conditions": "Clear", "description": "Clear conditions throughout the day.", "icon": "clear-day", "stations": ["KPUB", "72468094015", "72466093037", "72464093058", "KFCS", "KABH"], "source": "obs"}], "stations": {"KPUB": {"distance": 3885.0, "latitude": 38.28, "longitude": -104.52, "useCount": 0, "id": "KPUB", "name": "KPUB", "quality": 100, "contribution": 0.0}, "72468094015": {"distance": 47942.0, "latitude": 38.678, "longitude": -104.757, "useCount": 0, "id": "72468094015", "name": "FORT CARSON BUTTS ARMY AIR FIELD, CO US", "quality": 94, "contribution": 0.0}, "72466093037": {"distance": 60527.0, "latitude": 38.81, "longitude": -104.688, "useCount": 0, "id": "72466093037", "name": "COLORADO SPRINGS MUNICIPAL AIRPORT, CO US", "quality": 100, "contribution": 0.0}, "72464093058": {"distance": 5293.0, "latitude": 38.289, "longitude": -104.506, "useCount": 0, "id": "72464093058", "name": "PUEBLO MEMORIAL AIRPORT, CO US", "quality": 100, "contribution": 0.0}, "KFCS": {"distance": 48527.0, "latitude": 38.68, "longitude": -104.77, "useCount": 0, "id": "KFCS", "name": "KFCS", "quality": 100, "contribution": 0.0}, "KABH": {"distance": 59708.0, "latitude": 38.77, "longitude": -104.3, "useCount": 0, "id": "KABH", "name": "KABH", "quality": 98, "contribution": 0.0}}}