{"queryCost": 1, "latitude": 46.447, "longitude": -120.424, "resolvedAddress": "46.44700,-120.42400", "address": "46.44700,-120.42400", "timezone": "America/Los_Angeles", "tzoffset": -7.0, "days": [{"datetime": "2016-07-31", "datetimeEpoch": 1469948400, "tempmax": 90.1, "tempmin": 57.7, "temp": 75.3, "feelslikemax": 86.1, "feelslikemin": 57.7, "feelslike": 74.1, "dew": 40.0, "humidity": 30.5, "precip": 0.0, "precipprob": 0.0, "precipcover": 0.0, "preciptype": null, "snow": 0.0, "snowdepth": 0.0, "windgust": 32.2, "windspeed": 13.3, "winddir": 294.3, "pressure": 1011.3, "cloudcover": 0.2, "visibility": 9.9, "solarradiation": 346.4, "solarenergy": 29.8, "uvindex": 10.0, "sunrise": "05:42:18", "sunriseEpoch": 1469968938, "sunset": "20:33:00", "sunsetEpoch": 1470022380, "moonphase": 0.97, "conditions": "Clear", "description": "Clear conditions throughout the day.", "icon": "clear-day", "stations": ["KYKM", "K1YT", "72781024243", "K1S5", "72788324220", "KELN"], "source": "obs"}], "stations": {"KYKM": {"distance": 15920.0, "latitude": 46.57, "longitude": -120.53, "useCount": 0, "id": "KYKM", "name": "KYKM", "quality": 100, "contribution": 0.0}, "K1YT": {"distance": 23794.0, "latitude": 46.66, "longitude": -120.45, "useCount": 0, "id": "K1YT", "name": "K1YT", "quality": 87, "contribution": 0.0}, "72781024243": {"distance": 16293.0, "latitude": 46.568, "longitude": -120.543, "useCount": 0, "id": "72781024243", "name": "YAKIMA AIRPORT, WA US", "quality": 100, "contribution": 0.0}, "K1S5": {"distance": 37934.0, "latitude": 46.33, "longitude": -119.96, "useCount": 0, "id": "K1S5", "name": "K1S5", "quality": 99, "contribution": 0.0}, "72788324220": {"distance": 65832.0, "latitude": 47.034, "longitude": -120.53, "useCount": 0, "id": "72788324220", "name": "ELLENSBURG BOWERS FIELD, WA US", "quality": 100, "contribution": 0.0}, "KELN": {"distance": 65401.0, "latitude": 47.03, "longitude": -120.53, "useCount": 0, "id": "KELN", "name": "KELN", "quality": 98, "contribution": 0.0}}}