{"queryCost": 1, "latitude": 28.077, "longitude": -81.902, "resolvedAddress": "28.07700,-81.90200", "address": "28.07700,-81.90200", "timezone": "America/New_York", "tzoffset": -5.0, "days": [{"datetime": "2016-11-10", "datetimeEpoch": 1478754000, "tempmax": 80.9, "tempmin": 61.3, "temp": 69.6, "feelslikemax": 80.0, "feelslikemin": 61.3, "feelslike": 69.5, "dew": 55.7, "humidity": 65.9, "precip": 0.0, "precipprob": 0.0, "precipcover": 0.0, "preciptype": null, "snow": 0.0, "snowdepth": 0.0, "windgust": null, "windspeed": 7.8, "winddir": 53.3, "pressure": 1019.7, "cloudcover": 4.2, "visibility": 9.8, "solarradiation": 198.5, "solarenergy": 17.2, "uvindex": 8.0, "sunrise": "06:45:53", "sunriseEpoch": 1478778353, "sunset": "17:36:56", "sunsetEpoch": 1478817416, "moonphase": 0.39, "conditions": "Clear", "description": "Clear conditions throughout the day.", "icon": "clear-day", "stations": ["74793112876", "72037392824", "KGIF", "KPCM"], "source": "obs"}], "stations": {"74793112876": {"distance": 14611.0, "latitude": 28.062, "longitude": -81.754, "useCount": 0, "id": "74793112876", "name": "WINTER HAVEN GILBERT AIRPORT, FL US", "quality": 100, "contribution": 0.0}, "KGIF": {"distance": 15231.0, "latitude": 28.05, "longitude": -81.75, "useCount": 0, "id": "KGIF", "name": "KGIF", "quality": 100, "contribution": 0.0}, "72037392824": {"distance": 27140.0, "latitude": 28.0, "longitude": -82.164, "useCount": 0, "id": "72037392824", "name": "PLANT CITY MUNICIPAL AIRPORT, FL US", "quality": 99, "contribution": 0.0}, "KPCM": {"distance": 26760.0, "latitude": 28.0, "longitude": -82.16, "useCount": 0, "id": "KPCM", "name": "KPCM", "quality": 99, "contribution": 0.0}}}