{"queryCost": 1, "latitude": 40.45, "longitude": -122.29, "resolvedAddress": "40.45000,-122.29000", "address": "40.45000,-122.29000", "timezone": "America/Los_Angeles", "tzoffset": -7.0, "days": [{"datetime": "2017-03-26", "datetimeEpoch": 1490511600, "tempmax": 54.9, "tempmin": 48.8, "temp": 51.4, "feelslikemax": 54.9, "feelslikemin": 45.1, "feelslike": 50.7, "dew": 47.0, "humidity": 85.4, "precip": 0.45, "precipprob": 100.0, "precipcover": 41.67, "preciptype": ["rain"], "snow": 0.0, "snowdepth": 0.0, "windgust": 33.3, "windspeed": 17.1, "winddir": 178.9, "pressure": 1016.6, "cloudcover": 78.2, "visibility": 9.0, "solarradiation": 211.8, "solarenergy": 18.3, "uvindex": 8.0, "sunrise": "07:01:58", "sunriseEpoch": 1490536918, "sunset": "19:27:59", "sunsetEpoch": 1490581679, "moonphase": 0.99, "conditions": "Rain, Partially cloudy", "description": "Partly cloudy throughout the day with rain.", "icon": "rain", "stations": ["KO54", "KRBL", "KRDD", "72592024257", "99999904222", "72591024216"], "source": "obs"}], "stations": {"KO54": {"distance": 59140.0, "latitude": 40.71, "longitude": -122.9, "useCount": 0, "id": "KO54", "name": "KO54", "quality": 81, "contribution": 0.0}, "KRBL": {"distance": 33568.0, "latitude": 40.15, "longitude": -122.25, "useCount": 0, "id": "KRBL", "name": "KRBL", "quality": 100, "contribution": 0.0}, "KRDD": {"distance": 5630.0, "latitude": 40.5, "longitude": -122.3, "useCount": 0, "id": "KRDD", "name": "KRDD", "quality": 100, "contribution": 0.0}, "72592024257": {"distance": 7553.0, "latitude": 40.518, "longitude": -122.299, "useCount": 0, "id": "72592024257", "name": "REDDING MUNICIPAL AIRPORT, CA US", "quality": 100, "contribution": 0.0}, "99999904222": {"distance": 34901.0, "latitude": 40.651, "longitude": -122.607, "useCount": 0, "id": "99999904222", "name": "REDDING 12 WNW, CA US", "quality": 100, "contribution": 0.0}, "72591024216": {"distance": 33325.0, "latitude": 40.152, "longitude": -122.254, "useCount": 0, "id": "72591024216", "name": "RED BLUFF MUNICIPAL AIRPORT, CA US", "quality": 100, "contribution": 0.0}}}