{"queryCost": 1, "latitude": 38.611, "longitude": -121.383, "resolvedAddress": "38.61100,-121.38300", "address": "38.61100,-121.38300", "timezone": "America/Los_Angeles", "tzoffset": -7.0, "days": [{"datetime": "2017-08-30", "datetimeEpoch": 1504076400, "tempmax": 94.7, "tempmin": 59.5, "temp": 75.2, "feelslikemax": 91.2, "feelslikemin": 59.5, "feelslike": 74.4, "dew": 53.5, "humidity": 51.7, "precip": 0.0, "precipprob": 0.0, "precipcover": 0.0, "preciptype": null, "snow": 0.0, "snowdepth": 0.0, "windgust": null, "windspeed": 8.8, "winddir": 189.8, "pressure": 1009.0, "cloudcover": 0.7, "visibility": 9.9, "solarradiation": 303.3, "solarenergy": 26.1, "uvindex": 9.0, "sunrise": "06:33:13", "sunriseEpoch": 1504099993, "sunset": "19:38:07", "sunsetEpoch": 1504147087, "moonphase": 0.31, "conditions": "Clear", "description": "Clear conditions throughout the day.", "icon": "clear-day", "stations": ["KSMF", "72061400205", "72483023232", "72483993225", "KEDU", "KSAC"], "source": "obs"}], "stations": {"KSMF": {"distance": 19785.0, "latitude": 38.7, "longitude": -121.58, "useCount": 0, "id": "KSMF", "name": "SACRAMENTO METRO, CA", "quality": 100, "contribution": 0.0}, "72061400205": {"distance": 33289.0, "latitude": 38.909, "longitude": -121.351, "useCount": 0, "id": "72061400205", "name": "LINCOLN REGIONAL AIRPORT KARL HARDER FIELD, CA US", "quality": 100, "contribution": 0.0}, "72483023232": {"distance": 15144.0, "latitude": 38.507, "longitude": -121.495, "useCount": 0, "id": "72483023232", "name": "SACRAMENTO EXECUTIVE AIRPORT, CA US", "quality": 100, "contribution": 0.0}, "72483993225": {"distance": 20311.0, "latitude": 38.696, "longitude": -121.59, "useCount": 0, "id": "72483993225", "name": "SACRAMENTO METROPOLITAN AIRPORT, CA US", "quality": 100, "contribution": 0.0}, "KEDU": {"distance": 36552.0, "latitude": 38.53, "longitude": -121.79, "useCount": 0, "id": "KEDU", "name": "KEDU", "quality": 97, "contribution": 0.0}, "KSAC": {"distance": 14364.0, "latitude": 38.52, "longitude": -121.5, "useCount": 0, "id": "KSAC", "name": "KSAC", "quality": 100, "contribution": 0.0}}}