{"queryCost": 1, "latitude": 38.632, "longitude": -121.45, "resolvedAddress": "38.63200,-121.45000", "address": "38.63200,-121.45000", "timezone": "America/Los_Angeles", "tzoffset": -7.0, "days": [{"datetime": "2017-11-02", "datetimeEpoch": 1509606000, "tempmax": 64.6, "tempmin": 50.5, "temp": 57.7, "feelslikemax": 64.6, "feelslikemin": 50.5, "feelslike": 57.7, "dew": 48.6, "humidity": 72.9, "precip": 0.0, "precipprob": 0.0, "precipcover": 0.0, "preciptype": null, "snow": 0.0, "snowdepth": 0.0, "windgust": 17.2, "windspeed": 11.5, "winddir": 157.3, "pressure": 1015.5, "cloudcover": 67.9, "visibility": 9.6, "solarradiation": 144.0, "solarenergy": 12.4, "uvindex": 5.0, "sunrise": "07:34:00", "sunriseEpoch": 1509633240, "sunset": "18:04:08", "sunsetEpoch": 1509671048, "moonphase": 0.48, "conditions": "Partially cloudy", "description": "Partly cloudy throughout the day.", "icon": "partly-cloudy-day", "stations": ["KSMF", "72061400205", "72483023232", "72483993225", "KEDU", "KSAC"], "source": "obs"}], "stations": {"KSMF": {"distance": 13601.0, "latitude": 38.7, "longitude": -121.58, "useCount": 0, "id": "KSMF", "name": "SACRAMENTO METRO, CA", "quality": 100, "contribution": 0.0}, "72061400205": {"distance": 32010.0, "latitude": 38.909, "longitude": -121.351, "useCount": 0, "id": "72061400205", "name": "LINCOLN REGIONAL AIRPORT KARL HARDER FIELD, CA US", "quality": 100, "contribution": 0.0}, "72483023232": {"distance": 14466.0, "latitude": 38.507, "longitude": -121.495, "useCount": 0, "id": "72483023232", "name": "SACRAMENTO EXECUTIVE AIRPORT, CA US", "quality": 100, "contribution": 0.0}, "72483993225": {"distance": 14079.0, "latitude": 38.696, "longitude": -121.59, "useCount": 0, "id": "72483993225", "name": "SACRAMENTO METROPOLITAN AIRPORT, CA US", "quality": 100, "contribution": 0.0}, "KEDU": {"distance": 31691.0, "latitude": 38.53, "longitude": -121.79, "useCount": 0, "id": "KEDU", "name": "KEDU", "quality": 97, "contribution": 0.0}, "KSAC": {"distance": 13205.0, "latitude": 38.52, "longitude": -121.5, "useCount": 0, "id": "KSAC", "name": "KSAC", "quality": 100, "contribution": 0.0}}}