{"queryCost": 1, "latitude": 40.056, "longitude": -82.962, "resolvedAddress": "40.05600,-82.96200", "address": "40.05600,-82.96200", "timezone": "America/New_York", "tzoffset": -4.0, "days": [{"datetime": "2018-04-30", "datetimeEpoch": 1525060800, "tempmax": 69.6, "tempmin": 35.5, "temp": 53.6, "feelslikemax": 69.6, "feelslikemin": 34.0, "feelslike": 53.4, "dew": 27.6, "humidity": 43.2, "precip": 0.0, "precipprob": 0.0, "precipcover": 0.0, "preciptype": null, "snow": 0.0, "snowdepth": 0.0, "windgust": 16.1, "windspeed": 9.8, "winddir": 229.6, "pressure": 1024.4, "cloudcover": 0.3, "visibility": 9.9, "solarradiation": 341.5, "solarenergy": 29.4, "uvindex": 10.0, "sunrise": "06:32:59", "sunriseEpoch": 1525084379, "sunset": "20:25:45", "sunsetEpoch": 1525134345, "moonphase": 0.5, "conditions": "Clear", "description": "Clear conditions throughout the day.", "icon": "clear-day", "stations": ["KCMH", "KDLZ", "KOSU", "72428804804", "E5493", "72428014821"], "source": "obs"}], "stations": {"KCMH": {"distance": 9366.0, "latitude": 40.0, "longitude": -82.88, "useCount": 0, "id": "KCMH", "name": "KCMH", "quality": 100, "contribution": 0.0}, "KDLZ": {"distance": 29311.0, "latitude": 40.29, "longitude": -83.12, "useCount": 0, "id": "KDLZ", "name": "KDLZ", "quality": 100, "contribution": 0.0}, "KOSU": {"distance": 9581.0, "latitude": 40.08, "longitude": -83.07, "useCount": 0, "id": "KOSU", "name": "KOSU", "quality": 100, "contribution": 0.0}, "72428804804": {"distance": 10192.0, "latitude": 40.078, "longitude": -83.078, "useCount": 0, "id": "72428804804", "name": "COLUMBUS OHIO STATE UNIVERSITY AIRPORT, OH US", "quality": 100, "contribution": 0.0}, "E5493": {"distance": 8761.0, "latitude": 40.004, "longitude": -83.039, "useCount": 0, "id": "E5493", "name": "EW5493 Columbus OH US", "quality": 0, "contribution": 0.0}, "72428014821": {"distance": 10264.0, "latitude": 39.991, "longitude": -82.877, "useCount": 0, "id": "72428014821", "name": "PORT COLUMBUS INTERNATIONAL AIRPORT, OH US", "quality": 100, "contribution": 0.0}}}