{"queryCost": 1, "latitude": 36.008, "longitude": -86.382, "resolvedAddress": "36.00800,-86.38200", "address": "36.00800,-86.38200", "timezone": "America/Chicago", "tzoffset": -6.0, "days": [{"datetime": "2019-02-06", "datetimeEpoch": 1549432800, "tempmax": 69.0, "tempmin": 59.2, "temp": 64.3, "feelslikemax": 69.0, "feelslikemin": 59.2, "feelslike": 64.3, "dew": 61.8, "humidity": 91.6, "precip": 1.48, "precipprob": 100.0, "precipcover": 50.0, "preciptype": ["rain"], "snow": 0.0, "snowdepth": 0.0, "windgust": 30.8, "windspeed": 14.5, "winddir": 184.8, "pressure": 1006.5, "cloudcover": 86.3, "visibility": 7.9, "solarradiation": 26.8, "solarenergy": 2.3, "uvindex": 2.0, "sunrise": "06:42:06", "sunriseEpoch": 1549456926, "sunset": "17:17:32", "sunsetEpoch": 1549495052, "moonphase": 0.01, "conditions": "Rain, Partially cloudy", "description": "Partly cloudy throughout the day with rain.", "icon": "rain", "stations": ["72327013897", "KMQY", "KBNA", "72327313827", "F1358", "KSYI", "KRNC"], "source": "obs"}], "stations": {"72327013897": {"distance": 30275.0, "latitude": 36.119, "longitude": -86.689, "useCount": 0, "id": "72327013897", "name": "NASHVILLE INTERNATIONAL AIRPORT, TN US", "quality": 100, "contribution": 0.0}, "KMQY": {"distance": 12498.0, "latitude": 36.02, "longitude": -86.52, "useCount": 0, "id": "KMQY", "name": "KMQY", "quality": 100, "contribution": 0.0}, "KBNA": {"distance": 30057.0, "latitude": 36.13, "longitude": -86.68, "useCount": 0, "id": "KBNA", "name": "KBNA", "quality": 100, "contribution": 0.0}, "72327313827": {"distance": 12427.0, "latitude": 36.009, "longitude": -86.52, "useCount": 0, "id": "72327313827", "name": "SMYRNA AIRPORT, TN US", "quality": 100, "contribution": 0.0}, "F1358": {"distance": 12718.0, "latitude": 35.908, "longitude": -86.313, "useCount": 0, "id": "F1358", "name": "FW1358 Murfreesboro TN US", "quality": 0, "contribution": 0.0}, "KSYI": {"distance": 50145.0, "latitude": 35.56, "longitude": -86.44, "useCount": 0, "id": "KSYI", "name": "KSYI", "quality": 99, "contribution": 0.0}, "KRNC": {"distance": 58988.0, "latitude": 35.7, "longitude": -85.85, "useCount": 0, "id": "KRNC", "name": "KRNC", "quality": 100, "contribution": 0.0}}}