{"queryCost": 1, "latitude": 30.393, "longitude": -91.183, "resolvedAddress": "30.39300,-91.18300", "address": "30.39300,-91.18300", "timezone": "America/Chicago", "tzoffset": -5.0, "days": [{"datetime": "2020-07-20", "datetimeEpoch": 1595221200, "tempmax": 89.7, "tempmin": 77.0, "temp": 82.2, "feelslikemax": 99.1, "feelslikemin": 77.0, "feelslike": 87.2, "dew": 75.6, "humidity": 81.44, "precip": 0.0, "precipprob": null, "precipcover": 0.0, "preciptype": null, "snow": 0.0, "snowdepth": 0.0, "windgust": null, "windspeed": 10.3, "winddir": 88.0, "pressure": 1015.0, "cloudcover": 14.0, "visibility": 9.9, "solarradiation": 232.3, "solarenergy": 13.4, "uvindex": 6.0, "sunrise": "06:16:12", "sunriseEpoch": 1595243772, "sunset": "20:05:50", "sunsetEpoch": 1595293550, "moonphase": 1.0, "conditions": "Clear", "description": "Clear conditions throughout the day.", "icon": "clear-day", "stations": ["72104600460", "KBTR", "KHZR", "72232013970", "1313W", "72096700457", "LSU01"], "source": "obs"}], "stations": {"72104600460": {"distance": 33829.0, "latitude": 30.173, "longitude": -90.941, "useCount": 0, "id": "72104600460", "name": "LOUISIANA REGIONAL AIRPORT, LA US", "quality": 100, "contribution": 0.0}, "KBTR": {"distance": 15576.0, "latitude": 30.53, "longitude": -91.15, "useCount": 0, "id": "KBTR", "name": "KBTR", "quality": 100, "contribution": 0.0}, "KHZR": {"distance": 45342.0, "latitude": 30.71, "longitude": -91.48, "useCount": 0, "id": "KHZR", "name": "KHZR", "quality": 92, "contribution": 0.0}, "72232013970": {"distance": 16422.0, "latitude": 30.537, "longitude": -91.147, "useCount": 0, "id": "72232013970", "name": "BATON ROUGE METRO AIRPORT, LA US", "quality": 100, "contribution": 0.0}, "1313W": {"distance": 1585.0, "latitude": 30.407, "longitude": -91.187, "useCount": 0, "id": "1313W", "name": "Alex Box Stadium LA US WEATHERSTEM", "quality": 0, "contribution": 0.0}, "72096700457": {"distance": 45981.0, "latitude": 30.718, "longitude": -91.479, "useCount": 0, "id": "72096700457", "name": "FALSE RIVER REGIONAL AIRPORT, LA US", "quality": 86, "contribution": 0.0}, "LSU01": {"distance": 3523.0, "latitude": 30.364, "longitude": -91.167, "useCount": 0, "id": "LSU01", "name": "BenHur LA US", "quality": 0, "contribution": 0.0}}}