{"queryCost": 1, "latitude": 39.408, "longitude": -77.389, "resolvedAddress": "39.40800,-77.38900", "address": "39.40800,-77.38900", "timezone": "America/New_York", "tzoffset": -4.0, "days": [{"datetime": "2015-10-26", "datetimeEpoch": 1445832000, "tempmax": 60.7, "tempmin": 35.6, "temp": 45.0, "feelslikemax": 60.7, "feelslikemin": 35.6, "feelslike": 44.6, "dew": 38.0, "humidity": 79.9, "precip": 0.0, "precipprob": 0.0, "precipcover": 0.0, "preciptype": null, "snow": 0.0, "snowdepth": 0.0, "windgust": 20.8, "windspeed": 13.8, "winddir": 104.3, "pressure": 1030.6, "cloudcover": 0.0, "visibility": 9.5, "solarradiation": 128.0, "solarenergy": 11.1, "uvindex": 6.0, "sunrise": "07:30:42", "sunriseEpoch": 1445859042, "sunset": "18:15:45", "sunsetEpoch": 1445897745, "moonphase": 0.49, "conditions": "Clear", "description": "Clear conditions throughout the day.", "icon": "clear-day", "stations": ["72405503714", "KFDK", "KJYO", "KGAI", "72069903724", "72033493764"], "source": "obs"}], "stations": {"72405503714": {"distance": 39524.0, "latitude": 39.078, "longitude": -77.557, "useCount": 0, "id": "72405503714", "name": "LEESBURG EXECUTIVE AIRPORT, VA US", "quality": 98, "contribution": 0.0}, "KFDK": {"distance": 2111.0, "latitude": 39.42, "longitude": -77.37, "useCount": 0, "id": "KFDK", "name": "KFDK", "quality": 66, "contribution": 0.0}, "KJYO": {"distance": 39377.0, "latitude": 39.08, "longitude": -77.56, "useCount": 0, "id": "KJYO", "name": "KJYO", "quality": 98, "contribution": 0.0}, "KGAI": {"distance": 32526.0, "latitude": 39.17, "longitude": -77.17, "useCount": 0, "id": "KGAI", "name": "GAITHERSBURG, MD", "quality": 100, "contribution": 0.0}, "72069903724": {"distance": 39620.0, "latitude": 39.608, "longitude": -77.007, "useCount": 0, "id": "72069903724", "name": "WESTMINSTER CARROLL CO REGIONAL JB POAGE AIRPORT, MD US", "quality": 100, "contribution": 0.0}, "72033493764": {"distance": 32991.0, "latitude": 39.167, "longitude": -77.167, "useCount": 0, "id": "72033493764", "name": "GAITHERSBURG MONTGOMERY CO AIR PARK, MD US", "quality": 100, "contribution": 0.0}}}